yags/cli.py
yags/core.py
yags-0.0.1.dist-info/METADATA
yags-0.0.1.dist-info/WHEEL
yags-0.0.1.dist-info/entry_points.txt
yags-0.0.1.dist-info/top_level.txt
yags-0.0.1.dist-info/RECORD
