Metadata-Version: 2.4
Name: yags
Version: 0.0.1
Summary: An CLI tool to simplify squashing git commits.
Author-email: oha <aaronoh2015@gmail.com>
License-Expression: Apache-2.0
Project-URL: Homepage, https://github.com/duriantaco/yags
Classifier: Programming Language :: Python :: 3
Classifier: Operating System :: OS Independent
Classifier: Environment :: Console
Classifier: Topic :: Software Development :: Version Control :: Git
Requires-Python: >=3.9
Requires-Dist: click>=8.0
